{
  "active_publications_tracked": 30,
  "audit_run_id": "9592edae-ec2f-4cd2-9192-d8cf488e9b8f",
  "audited_at": "2026-03-28T23:24:09.243599Z",
  "dns_records_checked": 30,
  "findings": [
    {
      "check": "dns_resolution",
      "detail": "Expected DNS resolution to include ['100.64.0.1']; observed ['<missing>'].",
      "finding": "active_subdomain_missing_expected_public_resolution",
      "severity": "WARN",
      "subdomain": "git.lv3.org"
    },
    {
      "check": "private_route_probe",
      "detail": "Failed to connect to the declared private route target 100.64.0.1:5432: [Errno 61] Connection refused",
      "finding": "private_route_unreachable",
      "severity": "CRITICAL",
      "subdomain": "database.lv3.org"
    },
    {
      "check": "tls_certificate",
      "detail": "TLS certificate expires on 2026-03-29T11:15:05Z (0 days remaining).",
      "finding": "certificate_expiry_imminent",
      "severity": "CRITICAL",
      "subdomain": "vault.lv3.org"
    },
    {
      "check": "hetzner_zone",
      "detail": "Hetzner DNS exposes A 65.108.75.123 for registry.lv3.org, but the hostname is missing from the catalog.",
      "finding": "undeclared_subdomain_present_in_zone",
      "severity": "CRITICAL",
      "subdomain": "registry.lv3.org"
    },
    {
      "check": "hetzner_zone",
      "detail": "Catalog marks the hostname active, but no corresponding A/AAAA/CNAME record exists in Hetzner DNS.",
      "finding": "active_catalog_subdomain_missing_from_zone",
      "severity": "WARN",
      "subdomain": "git.lv3.org"
    }
  ],
  "hetzner_zone_records_checked": 46,
  "nginx_vhosts_checked": 25,
  "private_routes_checked": 4,
  "publications_in_catalog": 34,
  "registry_path": "/Users/live/Documents/GITHUB_PROJECTS/proxmox_florin_server/.worktrees/ws-0252-live-apply/config/subdomain-exposure-registry.json",
  "severity_counts": {
    "CRITICAL": 3,
    "WARN": 2
  }
}
