{
  "schema_version": "2.0.0",
  "created_at": "2026-04-08T00:16:29Z",
  "bypass": "skip_remote_gate",
  "source": "manual",
  "branch": "merge/workstreams-fixes",
  "commit": "98c6d34f416f97eb824907997b73a0f954d99aaf",
  "waiver": {
    "reason_code": "build_server_unreachable",
    "reason_summary": "The remote build-server gate could not be reached or stayed unavailable long enough to block the governed pre-push path.",
    "detail": "Build server at 10.10.10.30 is unreachable; local validation passed",
    "impacted_lanes": [
      "remote-gate"
    ],
    "substitute_evidence": [
      "Local pre-push validation completed successfully"
    ],
    "owner": "baditaflorin@gmail.com",
    "expires_on": "2026-04-10",
    "remediation_ref": "Fallback to local validation"
  }
}
