{
  "alert_contacts": [
    {
      "friendly_name": "lv3 operator email",
      "type": 2,
      "value": "operator@example.com"
    },
    {
      "friendly_name": "lv3 platform ops mattermost",
      "type": 5,
      "value_secret_id": "uptime_robot_mattermost_webhook"
    }
  ],
  "monitors": [
    {
      "friendly_name": "lv3 SSO Discovery",
      "type": 1,
      "url": "https://sso.lv3.org/realms/lv3/.well-known/openid-configuration",
      "interval": 300,
      "alert_contacts": [
        "lv3 operator email",
        "lv3 platform ops mattermost"
      ]
    },
    {
      "friendly_name": "lv3 Grafana Health",
      "type": 1,
      "url": "https://grafana.lv3.org/api/health",
      "interval": 300,
      "alert_contacts": [
        "lv3 operator email",
        "lv3 platform ops mattermost"
      ]
    },
    {
      "friendly_name": "lv3 Public Status Page",
      "type": 1,
      "url": "https://status.lv3.org",
      "interval": 300,
      "alert_contacts": [
        "lv3 operator email",
        "lv3 platform ops mattermost"
      ]
    }
  ]
}
